Metadata-Version: 1.1
Name: django-smart-collectstatic
Version: 0.1.0
Summary: UNIX command-line tool for bash/shell utils unit testing
Home-page: https://github.com/pahaz/django-smart-collectstatic
Author: Pahaz Blinov
Author-email: pahaz.blinov@gmail.com
License: MIT
Download-URL: https://pypi.python.org/packages/source/s/django-smart-collectstatic/django-smart-collectstatic-0.1.0.zip
Keywords: django smart collectstatic
Platform: unix
Platform: macos
Platform: windows
Classifier: Development Status :: 3 - Alpha
Classifier: Intended Audience :: Developers
Classifier: Topic :: Utilities
Classifier: License :: OSI Approved :: MIT License
Classifier: Programming Language :: Python :: 3.4
Classifier: Programming Language :: Python :: 3.5
